doctablex/__init__.py
doctablex/extractor.py
doctablex-1.0.0.dist-info/METADATA
doctablex-1.0.0.dist-info/WHEEL
doctablex-1.0.0.dist-info/top_level.txt
doctablex-1.0.0.dist-info/RECORD
