Metadata-Version: 2.4
Name: doctablex
Version: 1.0.0
Summary: Extract and clean tables from Word (.docx) files with regex-based type detection.
Home-page: https://github.com/faruqAI/doctablex
Author: Faruq Afolabi
Author-email: faruqafolabi@example.com
Classifier: Programming Language :: Python :: 3
Classifier: Topic :: Text Processing :: Linguistic
Classifier: Topic :: Office/Business :: Financial :: Spreadsheet
Classifier: License :: OSI Approved :: MIT License
Requires-Python: >=3.8
Requires-Dist: python-docx>=0.8.11
Requires-Dist: pandas>=2.0.0
Requires-Dist: python-dateutil>=2.8.2
Dynamic: author
Dynamic: author-email
Dynamic: classifier
Dynamic: description
Dynamic: description-content-type
Dynamic: home-page
Dynamic: requires-dist
Dynamic: requires-python
Dynamic: summary
